MANIFEST.in
README.rst
requirements.txt
setup.cfg
setup.py
yadi/__init__.py
yadi/bean_factories.py
yadi/context.py
yadi/context_impl.py
yadi/decorators.py
yadi/listeners.py
yadi/listeners_impl.py
yadi/types.py
yadi_framework.egg-info/PKG-INFO
yadi_framework.egg-info/SOURCES.txt
yadi_framework.egg-info/dependency_links.txt
yadi_framework.egg-info/not-zip-safe
yadi_framework.egg-info/requires.txt
yadi_framework.egg-info/top_level.txt