Metadata-Version: 1.1
Name: yadi-framework
Version: 0.0.6
Summary: YADI - Yet another dependency injection framework
Home-page: https://github.com/fcracker79/yadi
Author: fcracker79
Author-email: fcracker79@gmail.com
License: MIT
Keywords: dependency injection
Platform: UNKNOWN
Classifier: Development Status :: 3 - Alpha
Classifier: Intended Audience :: Developers
Classifier: Topic :: Software Development
Classifier: License :: OSI Approved :: MIT License
Classifier: Programming Language :: Python :: 3.5
Classifier: Programming Language :: Python :: 3.6
